limexhub/__init__.py
limexhub/restapi.py
limexhub-1.10.17.dist-info/licenses/LICENSE
limexhub-1.10.17.dist-info/METADATA
limexhub-1.10.17.dist-info/WHEEL
limexhub-1.10.17.dist-info/top_level.txt
limexhub-1.10.17.dist-info/RECORD
